nonebot_plugin_partner_join/__init__.py
nonebot_plugin_partner_join/config.py
nonebot_plugin_partner_join/background/background.gif
nonebot_plugin_partner_join-0.1.4.dist-info/LICENSE
nonebot_plugin_partner_join-0.1.4.dist-info/METADATA
nonebot_plugin_partner_join-0.1.4.dist-info/WHEEL
nonebot_plugin_partner_join-0.1.4.dist-info/top_level.txt
nonebot_plugin_partner_join-0.1.4.dist-info/RECORD
