Metadata-Version: 2.2
Name: nonebot-plugin-partner-join
Version: 0.1.4
Summary: NoneBot2 plugin used to generate maimaiDX travel companion add pictures (rotating gif) and can also be used to generate pictures similar to embed the corresponding circular frame (such as embedding the picture into the school badge).
Home-page: https://github.com/YuuzukiRin/nonebot_plugin_partner_join
Author: YuuzukiRin
Author-email: yuuzukirin@outlook.com
Classifier: Programming Language :: Python :: 3
Classifier: Programming Language :: Python :: 3.8
Classifier: Programming Language :: Python :: 3.9
Classifier: Programming Language :: Python :: 3.10
Classifier: License :: OSI Approved :: MIT License
Classifier: Operating System :: OS Independent
Requires-Python: >=3.8
License-File: LICENSE
Requires-Dist: nonebot2>=2.2.0
Requires-Dist: nonebot-adapter-onebot>=2.4.4
Requires-Dist: nonebot-plugin-alconna>=0.52.0
Requires-Dist: nonebot-plugin-apscheduler>=0.4.0
Requires-Dist: nonebot-plugin-localstore>=0.7.0
Requires-Dist: Pillow>=10.2.0
Requires-Dist: httpx<=0.27.2,>=0.27.0
Requires-Dist: tarina>=0.6.0
Dynamic: author
Dynamic: author-email
Dynamic: classifier
Dynamic: description
Dynamic: description-content-type
Dynamic: home-page
Dynamic: requires-dist
Dynamic: requires-python
Dynamic: summary
